{
  "name": "ANTOINE AUTO DEALER LTD",
  "total_issued_shares_value": 0,
  "total_authorised_shares_value": 1164.69,
  "authorised_shares": [],
  "involved_parties": {
    "Secretaries": [
      {
        "name": "ANTOINE VASSALLO\r",
        "nationality": "MALTESE",
        "party_id": "                                                            825847M",
        "address": "CASAVASSALLO,TRIQHAL-TARTARNI,RABATMALTA"
      }
    ],
    "Directors": [
      {
        "name": "ANTOINE VASSALLO\r",
        "nationality": "MALTESE",
        "party_id": "                                                            825847M",
        "address": "CASAVASSALLO,TRIQHAL-TARTARNI,RABATMALTA"
      },
      {
        "name": "MASSIMO VASSALLO\r",
        "nationality": "MALTESE",
        "party_id": "                                                            572777M",
        "address": "CASAVASSALLO,TRIQHAL-TARTARNI,RABATMALTA"
      }
    ],
    "Judicial Representatives": [
      {
        "name": "ANTOINE VASSALLO\r",
        "nationality": "MALTESE",
        "party_id": "                                                            825847M",
        "address": "CASAVASSALLO,TRIQHAL-TARTARNI,RABATMALTA"
      }
    ]
  },
  "total_issued_shares": 500,
  "address": "14, ENTRANCE B, ST. TROPHIMUS STREET,",
  "company_id": "C 26112",
  "registration_date": "Mar 27, 2000",
  "shares_currency": "EUR",
  "locality": "RABAT",
  "status": "",
  "total_authorised_shares": 500
}
