{
  "name": "AURA LTD.",
  "total_issued_shares_value": 1164.69,
  "total_authorised_shares_value": 11646.86,
  "authorised_shares": [
    {
      "issued_shares": 500,
      "type": "Ordinary",
      "authorised_share_capital": 5000,
      "nominal_value_per_share": 2.329373
    }
  ],
  "involved_parties": {
    "Secretaries": [
      {
        "name": "ANDREW FARRUGIA\r",
        "nationality": "MALTESE",
        "party_id": "                                                            76668M",
        "address": "KILLEENA,N/SOFFTRIQL-IMSAQQFIN,BAHARIC-CAGHAQ,NAXXARMALTA"
      }
    ],
    "Legal Representatives": [
      {
        "name": "ANDREW FARRUGIA\r",
        "nationality": "MALTESE",
        "party_id": "                                                            76668M",
        "address": "KILLEENA,N/SOFFTRIQL-IMSAQQFIN,BAHARIC-CAGHAQ,NAXXARMALTA"
      }
    ],
    "Directors": [
      {
        "name": "ANDREW FARRUGIA\r",
        "nationality": "MALTESE",
        "party_id": "                                                            76668M",
        "address": "KILLEENA,N/SOFFTRIQL-IMSAQQFIN,BAHARIC-CAGHAQ,NAXXARMALTA"
      },
      {
        "name": "ILSA FARRUGIA\r",
        "nationality": "BRITISH",
        "party_id": "                                                            33774A",
        "address": "'KILEENA',N/STRIQL-IMSAQQFIN,BAHARIC-CAGHAQ,NAXXARMALTA"
      }
    ],
    "Auditors": [
      {
        "name": "JESMOND PSAILA\r",
        "nationality": "MALTESE",
        "party_id": "                                                            01788",
        "address": "406,RUED'ARGENS,GZIRAGZR1361MALTA"
      }
    ],
    "Judicial Representatives": [
      {
        "name": "ANDREW FARRUGIA\r",
        "nationality": "MALTESE",
        "party_id": "                                                            76668M",
        "address": "KILLEENA,N/SOFFTRIQL-IMSAQQFIN,BAHARIC-CAGHAQ,NAXXARMALTA"
      }
    ],
    "Shareholders": [
      {
        "name": "ANDREW FARRUGIA\r",
        "nationality": "MALTESE",
        "party_id": "                                                            76668M",
        "address": "KILLEENA,N/SOFFTRIQL-IMSAQQFIN,BAHARIC-CAGHAQ,NAXXARMALTA",
        "shares": {
          "nominal_value_per_share": 2.329373,
          "paid_up_%": 20,
          "type": "Ordinary",
          "class": "",
          "issued_shares": 500
        }
      }
    ]
  },
  "total_issued_shares": 500,
  "address": "65, PORCIANA NO.3, HAWT STREET",
  "company_id": "C 29810",
  "registration_date": "Jun 03, 2002",
  "shares_currency": "EUR",
  "locality": "SWIEQI",
  "status": "",
  "total_authorised_shares": 5000
}
