{
  "name": "ASKARA SHIPPING LTD",
  "total_issued_shares_value": 1200,
  "total_authorised_shares_value": 1200,
  "authorised_shares": [
    {
      "issued_shares": 1200,
      "type": "Ordinary",
      "authorised_share_capital": 1200,
      "nominal_value_per_share": 1
    }
  ],
  "involved_parties": {
    "Judicial Representatives": [
      {
        "name": "ENGIN OKTAY\r",
        "nationality": "TURKISH",
        "party_id": "                                                            U02126390",
        "address": "SINPASLAGUNSITESIABDURRAHMANGAZIMAH,SEVENLERCAD.NO:6C4,SANCAKTEPE,ISTANBULTURKEY"
      },
      {
        "name": "AHMET T PAKSU\r",
        "nationality": "TURKISH",
        "party_id": "                                                            U08747475",
        "address": "CAYIRBASIMAH.SEDADKENT,KUME,EVLERINO:1060,ICKAPI,NO:MUSTAKIL,SARIYER,ISTANBULTURKEY"
      },
      {
        "name": "OSMAN NURETTIN PAKSU\r",
        "nationality": "TURKISH",
        "party_id": "                                                            U03192911",
        "address": "RESATBEYMAH.,62028SOK.,ABDURRAHIMGIZERAPT.GARAGIB-BLOK4/4,SEYHAN-ADANATURKEY"
      }
    ],
    "Directors": [
      {
        "name": "ENGIN OKTAY\r",
        "nationality": "TURKISH",
        "party_id": "                                                            U02126390",
        "address": "SINPASLAGUNSITESIABDURRAHMANGAZIMAH,SEVENLERCAD.NO:6C4,SANCAKTEPE,ISTANBULTURKEY"
      },
      {
        "name": "AHMET T PAKSU\r",
        "nationality": "TURKISH",
        "party_id": "                                                            U08747475",
        "address": "CAYIRBASIMAH.SEDADKENT,KUME,EVLERINO:1060,ICKAPI,NO:MUSTAKIL,SARIYER,ISTANBULTURKEY"
      },
      {
        "name": "OSMAN NURETTIN PAKSU\r",
        "nationality": "TURKISH",
        "party_id": "                                                            U03192911",
        "address": "RESATBEYMAH.,62028SOK.,ABDURRAHIMGIZERAPT.GARAGIB-BLOK4/4,SEYHAN-ADANATURKEY"
      }
    ],
    "Legal Representatives": [
      {
        "name": "ENGIN OKTAY\r",
        "nationality": "TURKISH",
        "party_id": "                                                            U02126390",
        "address": "SINPASLAGUNSITESIABDURRAHMANGAZIMAH,SEVENLERCAD.NO:6C4,SANCAKTEPE,ISTANBULTURKEY"
      },
      {
        "name": "AHMET T PAKSU\r",
        "nationality": "TURKISH",
        "party_id": "                                                            U08747475",
        "address": "CAYIRBASIMAH.SEDADKENT,KUME,EVLERINO:1060,ICKAPI,NO:MUSTAKIL,SARIYER,ISTANBULTURKEY"
      },
      {
        "name": "OSMAN NURETTIN PAKSU\r",
        "nationality": "TURKISH",
        "party_id": "                                                            U03192911",
        "address": "RESATBEYMAH.,62028SOK.,ABDURRAHIMGIZERAPT.GARAGIB-BLOK4/4,SEYHAN-ADANATURKEY"
      }
    ],
    "Shareholders": [
      {
        "name": "OSMAN CALIN\r",
        "nationality": "TURKISH",
        "party_id": "                                                            U01860996",
        "address": "CAMIMAH.,SEHITLERCAD.NO30/1TUZLA,ISTANBULTURKEY",
        "shares": {
          "nominal_value_per_share": 1,
          "paid_up_%": 20,
          "type": "Ordinary",
          "class": "",
          "issued_shares": 60
        }
      },
      {
        "name": "MEHMET GAZIOGLU\r",
        "nationality": "TURKISH",
        "party_id": "                                                            U04633339",
        "address": "SINPASLAGUNSITESIABDURRAHMANGAZIMAH,SEVENLERCAD.NO:6C12,SANCAKTEPE,ISTANBULTURKEY",
        "shares": {
          "nominal_value_per_share": 1,
          "paid_up_%": 20,
          "type": "Ordinary",
          "class": "",
          "issued_shares": 60
        }
      },
      {
        "name": "ENGIN OKTAY\r",
        "nationality": "TURKISH",
        "party_id": "                                                            U02126390",
        "address": "SINPASLAGUNSITESIABDURRAHMANGAZIMAH,SEVENLERCAD.NO:6C4,SANCAKTEPE,ISTANBULTURKEY",
        "shares": {
          "nominal_value_per_share": 1,
          "paid_up_%": 20,
          "type": "Ordinary",
          "class": "",
          "issued_shares": 60
        }
      },
      {
        "name": "HILAL NUR PAKSU\r",
        "nationality": "TURKISH",
        "party_id": "                                                            U02920106",
        "address": "SEDADKENTSITESI,BAHARSOK.,NO.1059,BUYUKDERE,SARIYER,ISTANBULTURKEY",
        "shares": {
          "nominal_value_per_share": 1,
          "paid_up_%": 20,
          "type": "Ordinary",
          "class": "",
          "issued_shares": 120
        }
      },
      {
        "name": "OSMAN NURETTIN PAKSU\r",
        "nationality": "TURKISH",
        "party_id": "                                                            U03192911",
        "address": "RESATBEYMAH.,62028SOK.,ABDURRAHIMGIZERAPT.GARAGIB-BLOK4/4,SEYHAN-ADANATURKEY",
        "shares": {
          "nominal_value_per_share": 1,
          "paid_up_%": 20,
          "type": "Ordinary",
          "class": "",
          "issued_shares": 900
        }
      }
    ]
  },
  "total_issued_shares": 1200,
  "address": "198, Old Bakery Street,",
  "company_id": "C 43831",
  "registration_date": "Mar 20, 2008",
  "shares_currency": "EUR",
  "locality": "VALLETTA",
  "status": "",
  "total_authorised_shares": 1200
}
