{
  "name": "ATTARD SERVICES (INVESTMENTS) LIMITED",
  "total_issued_shares_value": 1200,
  "total_authorised_shares_value": 1500,
  "authorised_shares": [
    {
      "issued_shares": 1200,
      "type": "Ordinary",
      "authorised_share_capital": 1500,
      "nominal_value_per_share": 1
    }
  ],
  "involved_parties": {
    "Secretaries": [
      {
        "name": "CAROLINE CURMI\r",
        "nationality": "MALTESE",
        "party_id": "                                                            171762M",
        "address": "3,ANNUNCIATIONSQUARE,SLIEMAMALTA"
      }
    ],
    "Legal Representatives": [
      {
        "name": "JOSEPHINE ATTARD\r",
        "nationality": "MALTESE",
        "party_id": "                                                            629934M",
        "address": "CAPITALMANSIONS,FLATA9CENSUXERRISTREET,TIGNESLIEMAMALTA"
      },
      {
        "name": "KENNETH ATTARD\r",
        "nationality": "MALTESE",
        "party_id": "                                                            229957M",
        "address": "MANYANA,TRIQL-GHARBIEL,SWIEQIMALTA"
      },
      {
        "name": "CAROLINE CURMI\r",
        "nationality": "MALTESE",
        "party_id": "                                                            171762M",
        "address": "3,ANNUNCIATIONSQUARE,SLIEMAMALTA"
      }
    ],
    "Directors": [
      {
        "name": "JOSEPHINE ATTARD\r",
        "nationality": "MALTESE",
        "party_id": "                                                            629934M",
        "address": "CAPITALMANSIONS,FLATA9CENSUXERRISTREET,TIGNESLIEMAMALTA"
      },
      {
        "name": "KENNETH ATTARD\r",
        "nationality": "MALTESE",
        "party_id": "                                                            229957M",
        "address": "MANYANA,TRIQL-GHARBIEL,SWIEQIMALTA"
      },
      {
        "name": "CAROLINE CURMI\r",
        "nationality": "MALTESE",
        "party_id": "                                                            171762M",
        "address": "3,ANNUNCIATIONSQUARE,SLIEMAMALTA"
      }
    ],
    "Auditors": [
      {
        "name": "PRICEWATERHOUSECOOPERS\r",
        "nationality": "",
        "party_id": "                                                             AB/26/84/38",
        "address": "78,MILLSTREET,QORMIMALTA"
      }
    ],
    "Judicial Representatives": [
      {
        "name": "JOSEPHINE ATTARD\r",
        "nationality": "MALTESE",
        "party_id": "                                                            629934M",
        "address": "CAPITALMANSIONS,FLATA9CENSUXERRISTREET,TIGNESLIEMAMALTA"
      },
      {
        "name": "KENNETH ATTARD\r",
        "nationality": "MALTESE",
        "party_id": "                                                            229957M",
        "address": "MANYANA,TRIQL-GHARBIEL,SWIEQIMALTA"
      },
      {
        "name": "CAROLINE CURMI\r",
        "nationality": "MALTESE",
        "party_id": "                                                            171762M",
        "address": "3,ANNUNCIATIONSQUARE,SLIEMAMALTA"
      }
    ],
    "Shareholders": [
      {
        "name": "GEORGE ATTARD\r",
        "nationality": "MALTESE",
        "party_id": "                                                            151255M",
        "address": "WINDHAVEN,TRIQL-ARZNU,MENSIJA,SANGWANNMALTA",
        "shares": {
          "nominal_value_per_share": 1,
          "paid_up_%": 100,
          "type": "Ordinary",
          "class": "",
          "issued_shares": 300
        }
      },
      {
        "name": "JOSEPHINE ATTARD\r",
        "nationality": "MALTESE",
        "party_id": "                                                            629934M",
        "address": "CAPITALMANSIONS,FLATA9CENSUXERRISTREET,TIGNESLIEMAMALTA",
        "shares": {
          "nominal_value_per_share": 1,
          "paid_up_%": 100,
          "type": "Ordinary",
          "class": "",
          "issued_shares": 300
        }
      },
      {
        "name": "KENNETH ATTARD\r",
        "nationality": "MALTESE",
        "party_id": "                                                            229957M",
        "address": "MANYANA,TRIQL-GHARBIEL,SWIEQIMALTA",
        "shares": {
          "nominal_value_per_share": 1,
          "paid_up_%": 100,
          "type": "Ordinary",
          "class": "",
          "issued_shares": 300
        }
      },
      {
        "name": "CAROLINE CURMI\r",
        "nationality": "MALTESE",
        "party_id": "                                                            171762M",
        "address": "3,ANNUNCIATIONSQUARESLIEMAMALTA",
        "shares": {
          "nominal_value_per_share": 1,
          "paid_up_%": 100,
          "type": "Ordinary",
          "class": "",
          "issued_shares": 300
        }
      }
    ]
  },
  "total_issued_shares": 1200,
  "address": "53 TANKS STREET",
  "company_id": "C 59628",
  "registration_date": "Mar 08, 2013",
  "shares_currency": "EUR",
  "locality": "BIRZEBBUGIA",
  "status": "",
  "total_authorised_shares": 1500
}
