{
  "name": "ANCHOR CONSULTING LIMITED",
  "total_issued_shares_value": 1201,
  "total_authorised_shares_value": 1201,
  "authorised_shares": [
    {
      "issued_shares": 1200,
      "type": "OrdinaryA",
      "authorised_share_capital": 1200,
      "nominal_value_per_share": 1
    },
    {
      "issued_shares": 1,
      "type": "OrdinaryB",
      "authorised_share_capital": 1,
      "nominal_value_per_share": 1
    }
  ],
  "involved_parties": {
    "Judicial Representatives": [
      {
        "name": "GRANT THORNTON FIDUCIAIRE LIMITED\r",
        "nationality": "",
        "party_id": "                                                            C 20650",
        "address": "TOWERBUSINESSCENTRE,TOWERSTREET,SWATAR,BIRKIRKARABKR4013MALTA"
      }
    ],
    "Directors": [
      {
        "name": "GRANT THORNTON FIDUCIAIRE LIMITED\r",
        "nationality": "",
        "party_id": "                                                            C 20650",
        "address": "TOWERBUSINESSCENTRE,TOWERSTREET,SWATAR,BIRKIRKARABKR4013MALTA"
      }
    ],
    "Secretaries": [
      {
        "name": "WAYNE PISANI\r",
        "nationality": "MALTESE",
        "party_id": "                                                            386878M",
        "address": "TORRITA'CINCLIBIDNIJA,L/OMOSTAMST5112MALTA"
      }
    ],
    "Legal Representatives": [
      {
        "name": "GRANT THORNTON FIDUCIAIRE LIMITED\r",
        "nationality": "",
        "party_id": "                                                            C 20650",
        "address": "TOWERBUSINESSCENTRE,TOWERSTREET,SWATAR,BIRKIRKARABKR4013MALTA"
      }
    ],
    "Shareholders": [
      {
        "name": "ANCHOR GROUP LIMITED\r",
        "nationality": "",
        "party_id": "                                                            C 61609",
        "address": "SUITE3,TOWERBUSINESSCENTRE,TOWERSTREET,SWATAR,BIRKIRKARAMALTA",
        "shares": {
          "nominal_value_per_share": 1,
          "paid_up_%": 100,
          "type": "Ordinary",
          "class": "A",
          "issued_shares": 1200
        }
      },
      {
        "name": "GRANT THORNTON FIDUCIAIRE LIMITED\r",
        "nationality": "",
        "party_id": "                                                            C 20650",
        "address": "TOWERBUSINESSCENTRE,TOWERSTREET,SWATAR,BIRKIRKARABKR4013MALTA",
        "shares": {
          "nominal_value_per_share": 1,
          "paid_up_%": 100,
          "type": "Ordinary",
          "class": "B",
          "issued_shares": 1
        }
      }
    ]
  },
  "total_issued_shares": 1201,
  "address": "SUITE 3, TOWER BUSINESS CENTRE, TOWER STREET, SWATAR,",
  "company_id": "C 61611",
  "registration_date": "Aug 20, 2013",
  "shares_currency": "EUR",
  "locality": "BIRKIRKARA",
  "status": "",
  "total_authorised_shares": 1201
}
