{
  "name": "BLUE GROTTO DEVELOPMENT CO. LIMITED",
  "involved_parties": {
    "Secretaries": [
      {
        "name": "CHRISTOPHER GALEA\r",
        "nationality": "MALTESE",
        "party_id": "                                                            837457M",
        "address": "TACRIS,GARDENCRESCENT,UPPERGARDENS,ST.JULIANSSTJ1923MALTA"
      }
    ],
    "Legal Representatives": [
      {
        "name": "ABACUS HOLDINGS LIMITED\r",
        "nationality": "",
        "party_id": "                                                            C 16564",
        "address": "93,MILLSTREET,QORMIQRM3102MALTA"
      }
    ],
    "Directors": [
      {
        "name": "ABACUS HOLDINGS LIMITED\r",
        "nationality": "",
        "party_id": "                                                            C 16564",
        "address": "93,MILLSTREET,QORMIQRM3102MALTA"
      }
    ],
    "Auditors": [
      {
        "name": "JOHN BORG\r",
        "nationality": "MALTESE",
        "party_id": "                                                            48046",
        "address": "40,TRIQMAITLAND,HAMRUNMALTA"
      }
    ],
    "Judicial Representatives": [
      {
        "name": "ABACUS HOLDINGS LIMITED\r",
        "nationality": "",
        "party_id": "                                                            C 16564",
        "address": "93,MILLSTREET,QORMIQRM3102MALTA"
      }
    ],
    "Shareholders": [
      {
        "name": "ABACUS HOLDINGS LIMITED\r",
        "nationality": "",
        "party_id": "                                                            C 16564",
        "address": "93,MILLSTREET,QORMIQRM3102MALTA",
        "shares": {
          "nominal_value_per_share": 1,
          "paid_up_%": 100,
          "type": "Ordinary",
          "class": "",
          "issued_shares": 1999
        }
      },
      {
        "name": "ABACUS HOLDINGS LIMITED\r",
        "nationality": "",
        "party_id": "                                                            C 16564",
        "address": "93,MILLSTREET,QORMIQRM3102MALTA",
        "shares": {
          "nominal_value_per_share": 1,
          "paid_up_%": 100,
          "type": "Ordinary",
          "class": "",
          "issued_shares": 1
        }
      }
    ]
  },
  "registration_date": "Company Status",
  "locality": "VALLETTA",
  "status": "",
  "company_id": "C 652",
  "address": "167, MERCHANTS STREET,"
}
