{
  "name": "BARTOLO BROTHERS HOLDINGS LTD",
  "total_issued_shares_value": 1200,
  "total_authorised_shares_value": 1200,
  "authorised_shares": [
    {
      "issued_shares": 1200,
      "type": "Ordinary",
      "authorised_share_capital": 1200,
      "nominal_value_per_share": 1
    }
  ],
  "involved_parties": {
    "Secretaries": [
      {
        "name": "ETIENNE BARTOLO\r",
        "nationality": "MALTESE",
        "party_id": "                                                            227778M",
        "address": "ORIANAFLAT1,TRIQL-GHENEBZEBBUGMALTA"
      }
    ],
    "Legal Representatives": [
      {
        "name": "ETIENNE BARTOLO\r",
        "nationality": "MALTESE",
        "party_id": "                                                            227778M",
        "address": "ORIANAFLAT1,TRIQL-GHENEBZEBBUGMALTA"
      },
      {
        "name": "MALCOLM BARTOLO\r",
        "nationality": "MALTESE",
        "party_id": "                                                            331484M",
        "address": "ORIANA,FLAT3,TRIQL-GHENEB,ZEBBUGZBG1520MALTA"
      }
    ],
    "Directors": [
      {
        "name": "ETIENNE BARTOLO\r",
        "nationality": "MALTESE",
        "party_id": "                                                            227778M",
        "address": "ORIANAFLAT1,TRIQL-GHENEBZEBBUGMALTA"
      },
      {
        "name": "MALCOLM BARTOLO\r",
        "nationality": "MALTESE",
        "party_id": "                                                            331484M",
        "address": "ORIANA,FLAT3,TRIQL-GHENEB,ZEBBUGZBG1520MALTA"
      }
    ],
    "Auditors": [
      {
        "name": "NEVILLE TRAPANI\r",
        "nationality": "MALTESE",
        "party_id": "                                                            11118",
        "address": "Office137TriqA.CaligariZABBARZBR2809MALTA"
      }
    ],
    "Judicial Representatives": [
      {
        "name": "ETIENNE BARTOLO\r",
        "nationality": "MALTESE",
        "party_id": "                                                            227778M",
        "address": "ORIANAFLAT1,TRIQL-GHENEBZEBBUGMALTA"
      },
      {
        "name": "MALCOLM BARTOLO\r",
        "nationality": "MALTESE",
        "party_id": "                                                            331484M",
        "address": "ORIANA,FLAT3,TRIQL-GHENEB,ZEBBUGZBG1520MALTA"
      }
    ],
    "Shareholders": [
      {
        "name": "ETIENNE BARTOLO\r",
        "nationality": "MALTESE",
        "party_id": "                                                            227778M",
        "address": "ORIANAFLAT1,TRIQL-GHENEBZEBBUGMALTA",
        "shares": {
          "nominal_value_per_share": 1,
          "paid_up_%": 100,
          "type": "Ordinary",
          "class": "",
          "issued_shares": 600
        }
      },
      {
        "name": "MALCOLM BARTOLO\r",
        "nationality": "MALTESE",
        "party_id": "                                                            331484M",
        "address": "ORIANA,FLAT3,TRIQL-GHENEB,ZEBBUGZBG1520MALTA",
        "shares": {
          "nominal_value_per_share": 1,
          "paid_up_%": 100,
          "type": "Ordinary",
          "class": "",
          "issued_shares": 600
        }
      }
    ]
  },
  "total_issued_shares": 1200,
  "address": "B&B CONSTRUCTION, SANTA MARIJA STREET, MAGHTAB",
  "company_id": "C 65983",
  "registration_date": "Jul 11, 2014",
  "shares_currency": "EUR",
  "locality": "NAXXAR",
  "status": "",
  "total_authorised_shares": 1200
}
