{
  "name": "A.B.M. IMPEX LTD",
  "total_issued_shares_value": 400000,
  "total_authorised_shares_value": 400000,
  "authorised_shares": [
    {
      "issued_shares": 400000,
      "type": "Ordinary",
      "authorised_share_capital": 400000,
      "nominal_value_per_share": 1
    }
  ],
  "involved_parties": {
    "Judicial Representatives": [
      {
        "name": "AYAD SALEH SALEM MUSSA\r",
        "nationality": "LIBYAN",
        "party_id": "                                                            N71810F9",
        "address": "5,TRIPOLISTREETMISURATASTATEOFLIBYA"
      },
      {
        "name": "ABDULSALAM ALSEDDIG ALI SHALLOUF\r",
        "nationality": "LIBYAN",
        "party_id": "                                                            P98JZC14",
        "address": "9,TRIPOLISTREET,MISURATASTATEOFLIBYA"
      },
      {
        "name": "ALBASHIR ASSEDDIG ALI SHALLOUF\r",
        "nationality": "LIBYAN",
        "party_id": "                                                            L4FFHLZ5",
        "address": "15,TRIPOLISTREET,MISURATASTATEOFLIBYA"
      },
      {
        "name": "MOHAMD ELSEDDIG ALI SHALLOUF\r",
        "nationality": "LIBYAN",
        "party_id": "                                                            HRP3Y84P",
        "address": "10,TRIPOLISTREET,MISURATASTATEOFLIBYA"
      }
    ],
    "Directors": [
      {
        "name": "AYAD SALEH SALEM MUSSA\r",
        "nationality": "LIBYAN",
        "party_id": "                                                            N71810F9",
        "address": "5,TRIPOLISTREETMISURATASTATEOFLIBYA"
      },
      {
        "name": "ABDULSALAM ALSEDDIG ALI SHALLOUF\r",
        "nationality": "LIBYAN",
        "party_id": "                                                            P98JZC14",
        "address": "9,TRIPOLISTREET,MISURATASTATEOFLIBYA"
      },
      {
        "name": "ALBASHIR ASSEDDIG ALI SHALLOUF\r",
        "nationality": "LIBYAN",
        "party_id": "                                                            L4FFHLZ5",
        "address": "15,TRIPOLISTREET,MISURATASTATEOFLIBYA"
      },
      {
        "name": "MOHAMD ELSEDDIG ALI SHALLOUF\r",
        "nationality": "LIBYAN",
        "party_id": "                                                            HRP3Y84P",
        "address": "10,TRIPOLISTREET,MISURATASTATEOFLIBYA"
      }
    ],
    "Secretaries": [
      {
        "name": "ABDULSALAM ALSEDDIG ALI SHALLOUF\r",
        "nationality": "LIBYAN",
        "party_id": "                                                            P98JZC14",
        "address": "9,TRIPOLISTREET,MISURATASTATEOFLIBYA"
      }
    ],
    "Legal Representatives": [
      {
        "name": "AYAD SALEH SALEM MUSSA\r",
        "nationality": "LIBYAN",
        "party_id": "                                                            N71810F9",
        "address": "5,TRIPOLISTREETMISURATASTATEOFLIBYA"
      },
      {
        "name": "ABDULSALAM ALSEDDIG ALI SHALLOUF\r",
        "nationality": "LIBYAN",
        "party_id": "                                                            P98JZC14",
        "address": "9,TRIPOLISTREET,MISURATASTATEOFLIBYA"
      },
      {
        "name": "ALBASHIR ASSEDDIG ALI SHALLOUF\r",
        "nationality": "LIBYAN",
        "party_id": "                                                            L4FFHLZ5",
        "address": "15,TRIPOLISTREET,MISURATASTATEOFLIBYA"
      },
      {
        "name": "MOHAMD ELSEDDIG ALI SHALLOUF\r",
        "nationality": "LIBYAN",
        "party_id": "                                                            HRP3Y84P",
        "address": "10,TRIPOLISTREET,MISURATASTATEOFLIBYA"
      }
    ],
    "Shareholders": [
      {
        "name": "AYAD SALEH SALEM MUSSA\r",
        "nationality": "LIBYAN",
        "party_id": "                                                            N71810F9",
        "address": "5,TRIPOLISTREETMISURATASTATEOFLIBYA",
        "shares": {
          "nominal_value_per_share": 1,
          "paid_up_%": 100,
          "type": "Ordinary",
          "class": "",
          "issued_shares": 100000
        }
      },
      {
        "name": "ABDULSALAM ALSEDDIG ALI SHALLOUF\r",
        "nationality": "LIBYAN",
        "party_id": "                                                            P98JZC14",
        "address": "9,TRIPOLISTREET,MISURATASTATEOFLIBYA",
        "shares": {
          "nominal_value_per_share": 1,
          "paid_up_%": 100,
          "type": "Ordinary",
          "class": "",
          "issued_shares": 100000
        }
      },
      {
        "name": "ALBASHIR ASSEDDIG ALI SHALLOUF\r",
        "nationality": "LIBYAN",
        "party_id": "                                                            L4FFHLZ5",
        "address": "15,TRIPOLISTREET,MISURATASTATEOFLIBYA",
        "shares": {
          "nominal_value_per_share": 1,
          "paid_up_%": 100,
          "type": "Ordinary",
          "class": "",
          "issued_shares": 100000
        }
      },
      {
        "name": "MOHAMD ELSEDDIG ALI SHALLOUF\r",
        "nationality": "LIBYAN",
        "party_id": "                                                            HRP3Y84P",
        "address": "10,TRIPOLISTREET,MISURATASTATEOFLIBYA",
        "shares": {
          "nominal_value_per_share": 1,
          "paid_up_%": 100,
          "type": "Ordinary",
          "class": "",
          "issued_shares": 100000
        }
      }
    ]
  },
  "total_issued_shares": 400000,
  "address": "15,  GROGNET STREET,",
  "company_id": "C 70495",
  "registration_date": "Jun 02, 2015",
  "shares_currency": "EUR",
  "locality": "MOSTA",
  "status": "",
  "total_authorised_shares": 400000
}
