{
  "name": "AVIOR SHIPPING LTD ( D 2317 )",
  "involved_parties": {
    "Judicial Representatives": [
      {
        "name": "GORAN CHEJKOV\r",
        "nationality": "MACEDONIAN",
        "party_id": "                                                            B0448368",
        "address": "NO69\"MATERDEI\",ST.RITASTREET,SLIEMASLM1487MALTA"
      }
    ],
    "Directors": [
      {
        "name": "GORAN CHEJKOV\r",
        "nationality": "MACEDONIAN",
        "party_id": "                                                            B0448368",
        "address": "NO69\"MATERDEI\",ST.RITASTREET,SLIEMASLM1487MALTA"
      }
    ],
    "Secretaries": [
      {
        "name": "ROBERTO COVIELLO\r",
        "nationality": "ITALIAN",
        "party_id": "                                                            82807A",
        "address": "DIANEFLAT4,WINDSORSTREET,SLIEMAMALTA"
      }
    ],
    "Legal Representatives": [
      {
        "name": "GORAN CHEJKOV\r",
        "nationality": "MACEDONIAN",
        "party_id": "                                                            B0448368",
        "address": "NO69\"MATERDEI\",ST.RITASTREET,SLIEMASLM1487MALTA"
      }
    ],
    "Shareholders": [
      {
        "name": "TRUSTFORTE FIDUCIARY LTD.\r",
        "nationality": "",
        "party_id": "                                                            C 25928",
        "address": "21A,PRINCESSMARGARETSTREET,MSIDAMSD1331MALTA",
        "shares": {
          "nominal_value_per_share": 1,
          "paid_up_%": 25,
          "type": "Ordinary",
          "class": "",
          "issued_shares": 1200
        }
      }
    ]
  },
  "registration_date": "Company Status",
  "locality": "VALLETTA",
  "status": "In Dissolution",
  "company_id": "C 7132",
  "address": "146/1 ST. LUCIA STREET"
}
