{
  "name": "AVIIK MEDIA LIMITED",
  "total_issued_shares_value": 1250,
  "total_authorised_shares_value": 1250,
  "authorised_shares": [
    {
      "issued_shares": 625,
      "type": "OrdinaryA",
      "authorised_share_capital": 625,
      "nominal_value_per_share": 1
    },
    {
      "issued_shares": 625,
      "type": "OrdinaryB",
      "authorised_share_capital": 625,
      "nominal_value_per_share": 1
    }
  ],
  "involved_parties": {
    "Judicial Representatives": [
      {
        "name": "VACLAV ELIAS\r",
        "nationality": "SLOVAK",
        "party_id": "                                                            BG8478443",
        "address": "11,BETHLEHEMHOUSE,LIMEHOUSECAUSEWAY,LONDONE148AGUNITEDKINGDOM"
      },
      {
        "name": "TOMAS HVIZDAK\r",
        "nationality": "SLOVAK",
        "party_id": "                                                            BA5422013",
        "address": "SVATOPLUKOVA33,PEZINOK90201SLOVAKIA"
      }
    ],
    "Directors": [
      {
        "name": "VACLAV ELIAS\r",
        "nationality": "SLOVAK",
        "party_id": "                                                            BG8478443",
        "address": "11,BETHLEHEMHOUSE,LIMEHOUSECAUSEWAY,LONDONE148AGUNITEDKINGDOM"
      },
      {
        "name": "TOMAS HVIZDAK\r",
        "nationality": "SLOVAK",
        "party_id": "                                                            BA5422013",
        "address": "SVATOPLUKOVA33,PEZINOK90201SLOVAKIA"
      }
    ],
    "Secretaries": [
      {
        "name": "TOMAS HVIZDAK\r",
        "nationality": "SLOVAK",
        "party_id": "                                                            BA5422013",
        "address": "SVATOPLUKOVA33,PEZINOK90201SLOVAKIA"
      }
    ],
    "Legal Representatives": [
      {
        "name": "VACLAV ELIAS\r",
        "nationality": "SLOVAK",
        "party_id": "                                                            BG8478443",
        "address": "11,BETHLEHEMHOUSE,LIMEHOUSECAUSEWAY,LONDONE148AGUNITEDKINGDOM"
      },
      {
        "name": "TOMAS HVIZDAK\r",
        "nationality": "SLOVAK",
        "party_id": "                                                            BA5422013",
        "address": "SVATOPLUKOVA33,PEZINOK90201SLOVAKIA"
      }
    ],
    "Shareholders": [
      {
        "name": "TOMAS HVIZDAK\r",
        "nationality": "SLOVAK",
        "party_id": "                                                            BA5422013",
        "address": "SVATOPLUKOVA33,PEZINOK90201SLOVAKIA",
        "shares": {
          "nominal_value_per_share": 1,
          "paid_up_%": 20,
          "type": "Ordinary",
          "class": "A",
          "issued_shares": 625
        }
      },
      {
        "name": "VACLAV ELIAS\r",
        "nationality": "SLOVAK",
        "party_id": "                                                            BG8478443",
        "address": "11,BETHLEHEMHOUSE,LIMEHOUSECAUSEWAY,LONDONE148AGUNITEDKINGDOM",
        "shares": {
          "nominal_value_per_share": 1,
          "paid_up_%": 20,
          "type": "Ordinary",
          "class": "B",
          "issued_shares": 625
        }
      }
    ]
  },
  "total_issued_shares": 1250,
  "address": "115 B, SUITE 3, OLD MINT STREET,",
  "company_id": "C 73724",
  "registration_date": "Dec 23, 2015",
  "shares_currency": "EUR",
  "locality": "VALLETTA",
  "status": "",
  "total_authorised_shares": 1250
}
