{
  "name": "AVIATION PARTS AND TRADING (AP&T) LIMITED",
  "total_issued_shares_value": 1500,
  "total_authorised_shares_value": 1500,
  "authorised_shares": [
    {
      "issued_shares": 1500,
      "type": "Ordinary",
      "authorised_share_capital": 1500,
      "nominal_value_per_share": 1
    }
  ],
  "involved_parties": {
    "Judicial Representatives": [
      {
        "name": "CHRISTIAN R.E. VAN HAUTE\r",
        "nationality": "BELGIAN",
        "party_id": "                                                            123900549652",
        "address": "1207EUROTOWERSEUROPORTROAD,GIBRALTARGIBRALTAR"
      },
      {
        "name": "HANS JOZEF VERBIST\r",
        "nationality": "BELGIAN",
        "party_id": "                                                            591-7480057-04",
        "address": "HAMERSTRAAT14,3201LANGDORPBELGIUM"
      }
    ],
    "Directors": [
      {
        "name": "CHRISTIAN R.E. VAN HAUTE\r",
        "nationality": "BELGIAN",
        "party_id": "                                                            123900549652",
        "address": "1207EUROTOWERSEUROPORTROAD,GIBRALTARGIBRALTAR"
      },
      {
        "name": "HANS JOZEF VERBIST\r",
        "nationality": "BELGIAN",
        "party_id": "                                                            591-7480057-04",
        "address": "HAMERSTRAAT14,3201LANGDORPBELGIUM"
      }
    ],
    "Secretaries": [
      {
        "name": "CHRISTIAN R.E. VAN HAUTE\r",
        "nationality": "BELGIAN",
        "party_id": "                                                            123900549652",
        "address": "1207EUROTOWERSEUROPORTROAD,GIBRALTARGIBRALTAR"
      }
    ],
    "Legal Representatives": [
      {
        "name": "CHRISTIAN R.E. VAN HAUTE\r",
        "nationality": "BELGIAN",
        "party_id": "                                                            123900549652",
        "address": "1207EUROTOWERSEUROPORTROAD,GIBRALTARGIBRALTAR"
      },
      {
        "name": "HANS JOZEF VERBIST\r",
        "nationality": "BELGIAN",
        "party_id": "                                                            591-7480057-04",
        "address": "HAMERSTRAAT14,3201LANGDORPBELGIUM"
      }
    ],
    "Shareholders": [
      {
        "name": "CHRISTIAN R.E. VAN HAUTE\r",
        "nationality": "BELGIAN",
        "party_id": "                                                            123900549652",
        "address": "1207EUROTOWERSEUROPORTROAD,GIBRALTARGIBRALTAR",
        "shares": {
          "nominal_value_per_share": 1,
          "paid_up_%": 20,
          "type": "Ordinary",
          "class": "",
          "issued_shares": 750
        }
      },
      {
        "name": "HANS JOZEF VERBIST\r",
        "nationality": "BELGIAN",
        "party_id": "                                                            591-7480057-04",
        "address": "HAMERSTRAAT14,3201LANGDORPBELGIUM",
        "shares": {
          "nominal_value_per_share": 1,
          "paid_up_%": 20,
          "type": "Ordinary",
          "class": "",
          "issued_shares": 750
        }
      }
    ]
  },
  "total_issued_shares": 1500,
  "address": "30, KENILWORTH, FLAT 3, SIR AUGUSTUS BARTOLO STREET,",
  "company_id": "C 80249",
  "registration_date": "Mar 30, 2017",
  "shares_currency": "EUR",
  "locality": "TA' XBIEX",
  "status": "",
  "total_authorised_shares": 1500
}
