{
  "name": "Andoria & Co.",
  "total_issued_shares_value": 0,
  "total_authorised_shares_value": 1167.02,
  "authorised_shares": [],
  "involved_parties": {
    "Directors": [
      {
        "name": "ALISON SCICLUNA\r",
        "nationality": "MALTESE",
        "party_id": "                                                            150067M",
        "address": "JANINA,TRIQTA'MARMORATHEVILLAGEST.JULIANSMALTA"
      },
      {
        "name": "ANDRE ZAMMIT\r",
        "nationality": "MALTESE",
        "party_id": "                                                            29130G",
        "address": "236/10,TOWERROADSLIEMAMALTA"
      },
      {
        "name": "VICTORIA ZAMMIT\r",
        "nationality": "MALTESE",
        "party_id": "                                                            679743M",
        "address": "236/10,TOWERROADSLIEMAMALTA"
      }
    ]
  },
  "total_issued_shares": 501,
  "address": "236/10 TOWER ROAD",
  "company_id": "P 1084",
  "registration_date": "Aug 18, 2006",
  "shares_currency": "EUR",
  "locality": "SLIEMA",
  "status": "",
  "total_authorised_shares": 501
}
