{
  "name": "AMALGAMATED INVESTMENTS SICAV P.L.C.",
  "involved_parties": {
    "Judicial Representatives": [
      {
        "name": "JUDE THADDEUS RAPA\r",
        "nationality": "MALTESE",
        "party_id": "                                                            45751G",
        "address": "131,DRANTONTABONESTREET,VICTORIA(GOZO)MALTA"
      },
      {
        "name": "MICHAEL ZAMMIT\r",
        "nationality": "MALTESE",
        "party_id": "                                                            31156G",
        "address": "'VILLAZAMMIT',POPEJOHNPAULIISTREETVICTORIA(GOZO)VCT04MALTA"
      }
    ],
    "Directors": [
      {
        "name": "FRANCESCO SIVE FRANK RAPA\r",
        "nationality": "MALTESE",
        "party_id": "                                                            40660G",
        "address": "FLAT2,GOVERNMENTHOUSINGESTATE,SANNATROAD,VICTORIA(GOZO)MALTA"
      },
      {
        "name": "MICHAEL ZAMMIT\r",
        "nationality": "MALTESE",
        "party_id": "                                                            31156G",
        "address": "'VILLAZAMMIT',POPEJOHNPAULIISTREETVICTORIA(GOZO)VCT04MALTA"
      }
    ],
    "Secretaries": [
      {
        "name": "VICTOR CAUCHI\r",
        "nationality": "MALTESE",
        "party_id": "                                                            59335G",
        "address": "FLAT2,13INDEPENDENCESQUARE,VICTORIA(GOZO)MALTA"
      }
    ],
    "Legal Representatives": [
      {
        "name": "JUDE THADDEUS RAPA\r",
        "nationality": "MALTESE",
        "party_id": "                                                            45751G",
        "address": "131,DRANTONTABONESTREET,VICTORIA(GOZO)MALTA"
      },
      {
        "name": "MICHAEL ZAMMIT\r",
        "nationality": "MALTESE",
        "party_id": "                                                            31156G",
        "address": "'VILLAZAMMIT',POPEJOHNPAULIISTREETVICTORIA(GOZO)VCT04MALTA"
      }
    ],
    "Shareholders": [
      {
        "name": "RAPA SHOWROOMS COMPANY LIMITED\r",
        "nationality": "",
        "party_id": "                                                            C 5076",
        "address": "RAPASHOWROOM,133,DR.ANTONTABONESTREETVICTORIA(GOZO)VCT10MALTA",
        "shares": {
          "nominal_value_per_share": 2.329373,
          "paid_up_%": 20,
          "type": "Ordinary",
          "class": "",
          "issued_shares": 5000
        }
      },
      {
        "name": "ROTCIV CO LTD\r",
        "nationality": "",
        "party_id": "                                                            C 9329",
        "address": "50,MARSALFORNROAD,XAGHRA(GOZO)MALTA",
        "shares": {
          "nominal_value_per_share": 2.329373,
          "paid_up_%": 20,
          "type": "Ordinary",
          "class": "",
          "issued_shares": 5000
        }
      },
      {
        "name": "TANDEM CORPORATION LTD\r",
        "nationality": "",
        "party_id": "                                                            C 11114",
        "address": "VILLAZAMMIT,POPEJOHNPAULIISTREET,VICTORIA(GOZO)MALTA",
        "shares": {
          "nominal_value_per_share": 2.329373,
          "paid_up_%": 20,
          "type": "Ordinary",
          "class": "",
          "issued_shares": 10000
        }
      }
    ]
  },
  "registration_date": "Company Status",
  "locality": "ST. JULIANS",
  "status": "",
  "company_id": "SV 13",
  "address": "Aragon House - Business Centre, Dragonara Road,"
}
